persist_to_disk/__init__.py
persist_to_disk/_utils.py
persist_to_disk/config.py
persist_to_disk/myfilelock.py
persist_to_disk/persister.py
persist_to_disk-0.0.7.dist-info/LICENSE
persist_to_disk-0.0.7.dist-info/METADATA
persist_to_disk-0.0.7.dist-info/WHEEL
persist_to_disk-0.0.7.dist-info/top_level.txt
persist_to_disk-0.0.7.dist-info/RECORD
