Metadata-Version: 2.1
Name: persist-to-disk
Version: 0.0.7
Summary: Persist expensive operations on disk.
Home-page: https://github.com/zlin7/python-persist_to_disk
Author: Zhen Lin
Author-email: zhenlin4@illinois.edu
License: MIT
Keywords: Cache,Persist
Platform: UNKNOWN
Requires-Dist: filelock (==3.9.0)
